bc_device_sdk-0.4.0.dist-info/METADATA
bc_device_sdk-0.4.0.dist-info/WHEEL
bc_device_sdk/__init__.py
bc_device_sdk/bc_device_sdk.pyd
bc_device_sdk-0.4.0.dist-info/RECORD
