Metadata-Version: 2.4
Name: bc_device_sdk
Version: 0.4.0
Summary: BrainCo FW proto message SDK
Author: BrainCo
License: 	
Project-URL: Source Code, https://github.com/BrainCoTech/bc_proto_sdk
